data_connectors_exchanges_coinapi/__init__.py
data_connectors_exchanges_coinapi/client/__init__.py
data_connectors_exchanges_coinapi/client/dispatching/__init__.py
data_connectors_exchanges_coinapi/client/dispatching/fallback_tso_price_signaler.py
data_connectors_exchanges_coinapi/client/dispatching/trading_symbol_data_dispatcher.py
data_connectors_exchanges_coinapi/client/processing/__init__.py
data_connectors_exchanges_coinapi/client/processing/exchange_data_processor.py
data_connectors_exchanges_coinapi/client/quality_assurance/__init__.py
data_connectors_exchanges_coinapi/client/quality_assurance/quality_assurance_monitor.py
data_connectors_exchanges_coinapi/client/shared_data_streamer.py
data_connectors_exchanges_coinapi/client/sourcing/__init__.py
data_connectors_exchanges_coinapi/client/sourcing/metadata.py
data_connectors_exchanges_coinapi/client/sourcing/websocket_data_connector.py
data_connectors_exchanges_coinapi/exceptions/__init__.py
data_connectors_exchanges_coinapi/execution/__init__.py
data_connectors_exchanges_coinapi/execution/executor.py
data_connectors_exchanges_coinapi/shared_setup.py
data_connectors_exchanges_coinapi-0.1.0.dist-info/METADATA
data_connectors_exchanges_coinapi-0.1.0.dist-info/WHEEL
data_connectors_exchanges_coinapi-0.1.0.dist-info/RECORD
