Metadata-Version: 2.1
Name: data-connectors-exchanges-coinapi
Version: 0.1.0
Summary: 
Author: Makhosonke Morafo
Author-email: makhosonke@komokun.org
Requires-Python: >=3.10,<3.11
Classifier: Programming Language :: Python :: 3
Classifier: Programming Language :: Python :: 3.10
Requires-Dist: numpy (>=1.26.4,<2.0.0)
Requires-Dist: requests (>=2.31.0,<3.0.0)
Requires-Dist: websockets (>=12.0,<13.0)
